{
  "cordova-plugin-statusbar": {
    "source": {
      "type": "registry",
      "id": "cordova-plugin-statusbar@2.4.2"
    },
    "is_top_level": true,
    "variables": {}
  },
  "cordova-plugin-device": {
    "source": {
      "type": "registry",
      "id": "cordova-plugin-device@2.0.2"
    },
    "is_top_level": true,
    "variables": {}
  },
  "cordova-plugin-splashscreen": {
    "source": {
      "type": "registry",
      "id": "cordova-plugin-splashscreen@5.0.2"
    },
    "is_top_level": true,
    "variables": {}
  },
  "cordova-plugin-ionic-webview": {
    "source": {
      "type": "registry",
      "id": "cordova-plugin-ionic-webview@^5.0.0"
    },
    "is_top_level": true,
    "variables": {}
  },
  "cordova-plugin-ionic-keyboard": {
    "source": {
      "type": "registry",
      "id": "cordova-plugin-ionic-keyboard@^2.0.5"
    },
    "is_top_level": true,
    "variables": {}
  },
  "cc.fovea.cordova.openwith": {
    "source": {
      "type": "registry",
      "id": "https://github.com/j3k0/cordova-plugin-openwith.git"
    },
    "is_top_level": true,
    "variables": {
      "ANDROID_MIME_TYPE": "text/*",
      "IOS_URL_SCHEME": "celebrate",
      "IOS_UNIFORM_TYPE_IDENTIFIER": "public.plain-text"
    }
  },
  "cordova-plugin-openwith": {
    "source": {
      "type": "registry",
      "id": "https://github.com/missive/cordova-plugin-openwith.git"
    },
    "is_top_level": true,
    "variables": {
      "ANDROID_MIME_TYPE": "text/*",
      "IOS_URL_SCHEME": "celebrate",
      "IOS_UNIFORM_TYPE_IDENTIFIER": "public.plain-text",
      "IOS_BUNDLE_IDENTIFIER": "io.celebrate.me.app"
    }
  }
}